README.rst
setup.py
aws_login/__init__.py
aws_login/__main__.py
aws_login/aws_login.py
aws_login.egg-info/PKG-INFO
aws_login.egg-info/SOURCES.txt
aws_login.egg-info/dependency_links.txt
aws_login.egg-info/entry_points.txt
aws_login.egg-info/not-zip-safe
aws_login.egg-info/requires.txt
aws_login.egg-info/top_level.txt