Metadata-Version: 1.0
Name: aws-login
Version: 0.1.1
Summary: AWS login using the Secure Token Service
Home-page: https://github.com/binxio/aws-login
Author: Martijn van Dongen
Author-email: martijnvandongen@binx.io
License: UNKNOWN
Platform: any
